websocks/__init__.py
websocks/__main__.py
websocks/algorithm.py
websocks/client.py
websocks/commands.py
websocks/config.py
websocks/exceptions.py
websocks/gfwlist.txt
websocks/gui.py
websocks/rule.py
websocks/server.py
websocks/socket.py
websocks/types.py
websocks/utils.py
websocks/whitelist.txt
websocks-0.4.6.dist-info/entry_points.txt
websocks-0.4.6.dist-info/LICENSE
websocks-0.4.6.dist-info/WHEEL
websocks-0.4.6.dist-info/METADATA
websocks-0.4.6.dist-info/RECORD
