Metadata-Version: 2.1
Name: websocks
Version: 0.4.6
Summary: A websocket-based socks5 proxy.
Home-page: https://github.com/abersheeran/websocks
License: MIT
Author: abersheeran
Author-email: me@abersheeran.com
Requires-Python: >=3.7,<4.0
Classifier: License :: OSI Approved :: MIT License
Classifier: Programming Language :: Python :: 3
Classifier: Programming Language :: Python :: 3.7
Classifier: Programming Language :: Python :: 3.8
Classifier: Programming Language :: Python :: 3.9
Classifier: Programming Language :: Python :: Implementation :: CPython
Provides-Extra: GUI
Requires-Dist: PySimpleGUIWx (>=0.17.2,<0.18.0); extra == "GUI"
Requires-Dist: aiodns (>=2.0.0,<3.0.0)
Requires-Dist: click (>=7.0,<8.0)
Requires-Dist: h11 (>=0.12.0,<0.13.0)
Requires-Dist: typing-extensions (>=3.7.4.1,<4.0.0.0); python_version < "3.8"
Requires-Dist: uvloop; sys_platform != "win32" and sys_platform != "cygwin" and platform_python_implementation != "pypy"
Requires-Dist: websockets (>=8.1,<9.0)
Project-URL: Documentation, https://github.com/abersheeran/websocks/wiki
Project-URL: Repository, https://github.com/abersheeran/websocks
